battery_boost/__init__.py
battery_boost/__main__.py
battery_boost/app.py
battery_boost/authenticate.py
battery_boost/constants.py
battery_boost/helper_functions.py
battery_boost/icons/tlp-battery-boost.png
battery_boost/shell_commands.py
battery_boost/tlp_parser.py
tlp_battery_boost-1.2.0.dist-info/METADATA
tlp_battery_boost-1.2.0.dist-info/WHEEL
tlp_battery_boost-1.2.0.dist-info/entry_points.txt
tlp_battery_boost-1.2.0.dist-info/licenses/LICENSE
tlp_battery_boost-1.2.0.dist-info/RECORD
