Metadata-Version: 2.4
Name: tlp-battery-boost
Version: 1.2.0
Summary: A lightweight Tkinter GUI to toggle TLP between normal and full-charge battery modes.
License-Expression: GPL-3.0
License-File: LICENSE
Keywords: battery,TLP,Linux,Tkinter,power,laptop
Author: Steve Daulton
Author-email: SteveDaulton@users.noreply.github.com
Requires-Python: >=3.10
Classifier: Development Status :: 5 - Production/Stable
Classifier: Environment :: X11 Applications :: GTK
Classifier: Intended Audience :: End Users/Desktop
Classifier: License :: OSI Approved :: GNU General Public License v3 (GPLv3)
Classifier: Operating System :: POSIX :: Linux
Classifier: Programming Language :: Python :: 3
Classifier: Programming Language :: Python :: 3.10
Classifier: Programming Language :: Python :: 3.11
Classifier: Programming Language :: Python :: 3.12
Classifier: Programming Language :: Python :: 3.13
Classifier: Topic :: Desktop Environment
Classifier: Topic :: Utilities
Project-URL: Documentation, https://stevedaulton.github.io/tlp-battery-boost/
Project-URL: Homepage, https://github.com/SteveDaulton/tlp-battery-boost
Project-URL: Repository, https://github.com/SteveDaulton/tlp-battery-boost
